ag_kit_py/__init__.py
ag_kit_py/main.py
ag_kit_py-0.0.1.dist-info/METADATA
ag_kit_py-0.0.1.dist-info/WHEEL
ag_kit_py-0.0.1.dist-info/RECORD
