Metadata-Version: 2.4
Name: ag-kit-py
Version: 0.0.1
Summary: ag-kit-py
Requires-Python: >=3.11
Provides-Extra: dev
Requires-Dist: pytest>=7.0.0; extra == 'dev'
Requires-Dist: ruff>=0.1.0; extra == 'dev'
